astropt/__init__.py
astropt/_version.py
astropt/configurator.py
astropt/local_datasets.py
astropt/model.py
astropt/model_utils.py
astropt-2.0.9.dist-info/METADATA
astropt-2.0.9.dist-info/WHEEL
astropt-2.0.9.dist-info/licenses/COPYING.md
astropt-2.0.9.dist-info/RECORD
