Metadata-Version: 2.4
Name: astropt
Version: 2.0.9
Summary: Transformer based foundation model for galaxy images (and general astronomy)
Project-URL: Homepage, https://github.com/smith42/astropt
Project-URL: Issues, https://github.com/smith42/astropt/issues
Author-email: "Michael J. Smith" <mike@mjjsmith.com>
License-File: COPYING.md
Keywords: astronomy,astrophysics,astropt,pytorch,scientific computing
Classifier: Intended Audience :: Science/Research
Classifier: License :: OSI Approved :: GNU Affero General Public License v3 or later (AGPLv3+)
Classifier: Operating System :: OS Independent
Classifier: Programming Language :: Python :: 3
Requires-Python: >=3.10
Requires-Dist: astropy
Requires-Dist: datasets>=3.1.0
Requires-Dist: einops>=0.8.0
Requires-Dist: h5py>=3.12.1
Requires-Dist: loralib
Requires-Dist: matplotlib>=3.9.2
Requires-Dist: multiprocess>=0.70.16
Requires-Dist: numpy>=1.26.3
Requires-Dist: pandas>=2.2.3
Requires-Dist: pre-commit>=4.2.0
Requires-Dist: scikit-learn>=1.5.2
Requires-Dist: scipy>=1.14.1
Requires-Dist: slack-sdk>=3.33.4
Requires-Dist: tiktoken>=0.8.0
Requires-Dist: torch
Requires-Dist: torchvision
Requires-Dist: tqdm>=4.67.1
Requires-Dist: traces>=0.6.4
Requires-Dist: wandb>=0.18.7
